Metadata-Version: 1.0
Name: adevinta-yapo-bi-pySpark-postgresql
Version: 0.0.0.0.48
Summary: Class develop to improving access to pySpark functions.
Home-page: https://github.mpi-internal.com/Yapo/bi-insights
Author: Yapo BI
Author-email: bi.insights@yapo.cl
License: MIT
Platform: UNKNOWN
